disvoice_glottal/GCI.py
disvoice_glottal/__init__.py
disvoice_glottal/glottal.py
disvoice_glottal/peakdetect.py
disvoice_glottal/utils_gci.py
disvoice_glottalLP/GCI.py
disvoice_glottalLP/__init__.py
disvoice_glottalLP/glottal.py
disvoice_glottalLP/peakdetect.py
disvoice_glottalLP/utils_gci.py
disvoice_glottalLP-0.0.1.dist-info/METADATA
disvoice_glottalLP-0.0.1.dist-info/WHEEL
disvoice_glottalLP-0.0.1.dist-info/top_level.txt
disvoice_glottalLP-0.0.1.dist-info/RECORD
