Metadata-Version: 2.1
Name: disvoice-glottalLP
Version: 0.0.1
Summary: A pip installable version of the glottal function from  jcvazquezc's DisVoice library
Home-page: https://github.com/lurein/DisVoice
Author: Lurein Perera
Author-email: lureinperera@gmail.com
License: UNKNOWN
Platform: UNKNOWN
Classifier: Programming Language :: Python :: 3
Classifier: License :: OSI Approved :: MIT License
Classifier: Operating System :: OS Independent
